CHANGES.rst
LICENSE
MANIFEST.in
README.rst
setup.py
django_hits/__init__.py
django_hits/models.py
django_hits/utils.py
django_hits.egg-info/PKG-INFO
django_hits.egg-info/SOURCES.txt
django_hits.egg-info/dependency_links.txt
django_hits.egg-info/requires.txt
django_hits.egg-info/top_level.txt
django_hits/management/__init__.py
django_hits/management/commands/__init__.py
django_hits/management/commands/hits_create_history.py
django_hits/migrations/0001_initial.py
django_hits/migrations/0002_add_bucket.py
django_hits/migrations/0003_added_history.py
django_hits/migrations/0004_auto__chg_field_hitlog_ip.py
django_hits/migrations/__init__.py
django_hits/templatetags/__init__.py
django_hits/templatetags/hit_tags.py
tests/__init__.py
tests/__init__.pyc
tests/requirements.txt
tests/settings.py
tests/settings.pyc
tests/test_basics.py
tests/test_smoke.py
tests/__pycache__/__init__.cpython-34.pyc
tests/__pycache__/settings.cpython-34.pyc
tests/__pycache__/test_basics.cpython-27-PYTEST.pyc
tests/__pycache__/test_basics.cpython-34-PYTEST.pyc
tests/__pycache__/test_basics.pypy-27-PYTEST.pyc
tests/__pycache__/test_smoke.cpython-27-PYTEST.pyc
tests/__pycache__/test_smoke.cpython-34-PYTEST.pyc
tests/__pycache__/test_smoke.pypy-27-PYTEST.pyc